simplycli/__init__.py
simplycli/arg.py
simplycli/bundle.py
simplycli/cli.py
simplycli/decorators.py
simplycli/meta.py
simply_cli-0.1.3.dist-info/METADATA
simply_cli-0.1.3.dist-info/WHEEL
simply_cli-0.1.3.dist-info/licenses/LICENSE
simply_cli-0.1.3.dist-info/RECORD
