Metadata-Version: 2.3
Name: simply-cli
Version: 0.1.3
Summary: A simple framework for building method-based reactive CLIs.
Project-URL: homepage, https://github.com/ImaMapleTree/simply-cli
Author: Evan Cowin
License-Expression: MIT
License-File: LICENSE
Classifier: License :: OSI Approved :: MIT License
Classifier: Operating System :: OS Independent
Classifier: Programming Language :: Python :: 3
Requires-Python: >=3.7
